bookrecs/__init__.py
bookrecs/utils.py
bookrecs/api/__init__.py
bookrecs/api/api.py
bookrecs/db/__init__.py
bookrecs/db/data_generator.py
bookrecs/db/schema.py
bookrecs/db/sql_interactions.py
bookrecs/logger/__init__.py
bookrecs/logger/logger.py
bookrecs/model/__init__.py
bookrecs/model/model.py
bookrecs-0.1.6.dist-info/METADATA
bookrecs-0.1.6.dist-info/WHEEL
bookrecs-0.1.6.dist-info/top_level.txt
bookrecs-0.1.6.dist-info/RECORD
