Metadata-Version: 2.1
Name: bookrecs
Version: 0.1.6
Summary: BookStore Recommendation System
Home-page: UNKNOWN
Author: Mane Davtyan
Author-email: UNKNOWN
License: UNKNOWN
Platform: UNKNOWN
Requires-Dist: fastapi (==0.105.0)
Requires-Dist: numpy (==1.24.4)
Requires-Dist: pandas (==2.0.3)
Requires-Dist: pydantic (==2.5.2)
Requires-Dist: scikit-learn (==1.3.2)
Requires-Dist: setuptools (==41.2.0)
Requires-Dist: SQLAlchemy (==2.0.23)
Requires-Dist: uvicorn (==0.24.0.post1)
